Workbook

Sheet Cover Page
D13: Snowflake SaaS Operating Model & Revenue Retention Forecast
D15: Company: Snowflake Inc.
D16: Ticker: SNOW
D17: Sector: Cloud Software / Data Infrastructure
D18: Model Type: SaaS Operating Model
D19: Forecast Period: FY2027E–FY2030E

Sheet Historical Financials
A1: Snowflake Historical Financials
A2: Figures in $ millions unless otherwise stated
A3: Metric | B3: FY2024A | C3: FY2025A | D3: FY2026A
A4: Revenue | B4: 2806.5 | C4: 3626.4 | D4: 4683.9
A5: Product Revenue | B5: 2666.8 | C5: 3462.4 | D5: 4472.3
A6: Professional Services & Other Revenue | B6: 139.6 | C6: 164 | D6: 211.6
A7: Cost of Revenue | B7: 898.6 | C7: 1214.7 | D7: 1537.8
A8: Gross Profit | B8: 1907.9 | C8: 2411.7 | D8: 3146.1
A9: Sales & Marketing | B9: 1391.7 | C9: 1672.1 | D9: 2062.1
A10: Research & Development | B10: 1287.9 | C10: 1783.4 | D10: 1969.5
A11: General & Administrative | B11: 323 | C11: 412.3 | D11: 549.7
A12: Total Operating Expenses | B12: 3002.7 | C12: 3867.7 | D12: 4581.3
A13: Operating Income / Loss | B13: -1094.8 | C13: -1456 | D13: -1435.2
A14: Net Income / Loss | B14: -838 | C14: -1289.2 | D14: -1329
A15: Cash Flow from Operations | B15: 848.1 | C15: 959.8 | D15: 1221.9
A16: Free Cash Flow | B16: 778.9 | C16: 884.1 | D16: 1120.3

Sheet Saas Metrics
A1: Snowflake SaaS Metrics
A2: Figures in $ millions unless otherwise stated
A3: Metric | B3: FY2024A | C3: FY2025A | D3: FY2026A
A4: Product Revenue | B4: ='Historical Financials'!B5 -> 2666.8 | C4: ='Historical Financials'!C5 -> 3462.4 | D4: ='Historical Financials'!D5 -> 4472.3
A5: Product Revenue Growth | B5: - | C5: =C4/B4-1 -> 0.29833508 | D5: =D4/C4-1 -> 0.29167629
A6: Net Revenue Retention | B6: 1.33 | C6: 1.26 | D6: 1.25
A7: Customers > $1M Product Revenue | B7: 449 | C7: 576 | D7: 733
A8: Customer Growth > $1M | B8: - | C8: =C7/B7-1 -> 0.28285078 | D8: =D7/C7-1 -> 0.27256944
A9: Forbes Global 2000 Customers | B9: 716 | C9: 750 | D9: 790
A10: Remaining Performance Obligations | B10: 5174.7 | C10: 6867.5 | D10: 9771.5
A11: RPO Growth | B11: - | C11: =C10/B10-1 -> 0.32713008 | D11: =D10/C10-1 -> 0.4228613
A12: RPO / Revenue | B12: =B10/'Historical Financials'!B4 -> 1.8438268 | C12: =C10/'Historical Financials'!C4 -> 1.8937514 | D12: =D10/'Historical Financials'!D4 -> 2.0861889
A13: Free Cash Flow | B13: ='Historical Financials'!B16 -> 778.9 | C13: ='Historical Financials'!C16 -> 884.1 | D13: ='Historical Financials'!D16 -> 1120.3
A14: Free Cash Flow Margin | B14: =B13/'Historical Financials'!B4 -> 0.2775343 | C14: =C13/'Historical Financials'!C4 -> 0.2437955 | D14: =D13/'Historical Financials'!D4 -> 0.23918102

Sheet Revenue Build
A1: Snowflake Revenue Build
A2: Figures in $ millions unless otherwise stated
A3: Metric | B3: FY2026A | C3: FY2027E | D3: FY2028E | E3: FY2029E | F3: FY2030E
A4: Product Revenue | B4: ='Saas Metrics'!D4 -> 4472.3 | C4: =B4*(1+C5) -> 5590.375 | D4: =C4*(1+D5) -> 6820.2575 | E4: =D4*(1+E5) -> 8184.309 | F4: =E4*(1+F5) -> 9657.4846
A5: Product Revenue Growth | B5: ='Saas Metrics'!D5 -> 0.29167629 | C5: 0.25 | D5: 0.22 | E5: 0.2 | F5: 0.18
A6: Professional Services & Other Revenue | B6: ='Historical Financials'!D6 -> 211.6 | C6: =B6*(1+C7) -> 232.76 | D6: =C6*(1+D7) -> 251.3808 | E6: =D6*(1+E7) -> 266.46365 | F6: =E6*(1+F7) -> 279.78683
A7: Professional Services & Other Revenue Growth | B7: 0.29 | C7: 0.1 | D7: 0.08 | E7: 0.06 | F7: 0.05
A8: Total Revenue | B8: =B4+B6 -> 4683.9 | C8: =C4+C6 -> 5823.135 | D8: =D4+D6 -> 7071.6383 | E8: =E4+E6 -> 8450.7726 | F8: =F4+F6 -> 9937.2715
A9: Total Revenue Growth | B9: - | C9: =C8/B8-1 -> 0.2432236 | D9: =D8/C8-1 -> 0.21440398 | E9: =E8/D8-1 -> 0.19502332 | F9: =F8/E8-1 -> 0.17590093

Sheet Operating Model
A1: Snowflake Operating Model
A2: Figures in $ millions unless otherwise stated
A3: Metric | B3: FY2026A | C3: FY2027E | D3: FY2028E | E3: FY2029E | F3: FY2030E
A4: Product Revenue | B4: ='Revenue Build'!B4 -> 4472.3 | C4: ='Revenue Build'!C4 -> 5590.375 | D4: ='Revenue Build'!D4 -> 6820.2575 | E4: ='Revenue Build'!E4 -> 8184.309 | F4: ='Revenue Build'!F4 -> 9657.4846
A5: Product Revenue Growth | B5: - | C5: 0.25 | D5: 0.22 | E5: 0.2 | F5: 0.18
A6: Professional Services & Other Revenue | B6: ='Revenue Build'!B6 -> 211.6 | C6: ='Revenue Build'!C6 -> 232.76 | D6: ='Revenue Build'!D6 -> 251.3808 | E6: ='Revenue Build'!E6 -> 266.46365 | F6: ='Revenue Build'!F6 -> 279.78683
A7: Professional Services & Other Revenue Growth | B7: - | C7: 0.1 | D7: 0.08 | E7: 0.06 | F7: 0.05
A8: Total Revenue | B8: ='Revenue Build'!B8 -> 4683.9 | C8: ='Revenue Build'!C8 -> 5823.135 | D8: ='Revenue Build'!D8 -> 7071.6383 | E8: ='Revenue Build'!E8 -> 8450.7726 | F8: ='Revenue Build'!F8 -> 9937.2715
A9: Product Gross Margin | B9: 0.72 | C9: 0.75 | D9: 0.76 | E9: 0.77 | F9: 0.78
A10: Product Gross Profit | B10: 3220.1 | C10: =C4*C9 -> 4192.7812 | D10: =D4*D9 -> 5183.3957 | E10: =E4*E9 -> 6301.9179 | F10: =F4*F9 -> 7532.838
A11: Services Gross Margin | B11: =B12/B6 -> -0.34971645 | C11: -0.1 | D11: -0.05 | E11: 0 | F11: 0
A12: Services Gross Profit | B12: =B13-B10 -> -74 | C12: =C6*C11 -> -23.276 | D12: =D6*D11 -> -12.56904 | E12: =E6*E11 -> 0 | F12: =F6*F11 -> 0
A13: Total Gross Profit | B13: ='Historical Financials'!D8 -> 3146.1 | C13: =C10+C12 -> 4169.5053 | D13: =D10+D12 -> 5170.8267 | E13: =E10+E12 -> 6301.9179 | F13: =F10+F12 -> 7532.838
A14: Gross Margin % | B14: =B13/B8 -> 0.67168385 | C14: =C13/C8 -> 0.71602414 | D14: =D13/D8 -> 0.73120633 | E14: =E13/E8 -> 0.74572092 | F14: =F13/F8 -> 0.75803887
A15: Sales & Marketing % of Revenue | B15: =B16/B8 -> 0.44025278 | C15: 0.33 | D15: 0.32 | E15: 0.31 | F15: 0.3
A16: Sales & Marketing | B16: ='Historical Financials'!D9 -> 2062.1 | C16: =C8*C15 -> 1921.6346 | D16: =D8*D15 -> 2262.9243 | E16: =E8*E15 -> 2619.7395 | F16: =F8*F15 -> 2981.1814
A17: Research & Development % of Revenue | B17: =B18/B8 -> 0.42048293 | C17: 0.19 | D17: 0.185 | E17: 0.18 | F17: 0.175
A18: Research & Development | B18: ='Historical Financials'!D10 -> 1969.5 | C18: =C8*C17 -> 1106.3957 | D18: =D8*D17 -> 1308.2531 | E18: =E8*E17 -> 1521.1391 | F18: =F8*F17 -> 1739.0225
A19: General & Administrative % of Revenue | B19: =B20/B8 -> 0.11735947 | C19: 0.058 | D19: 0.055 | E19: 0.053 | F19: 0.05
A20: General & Administrative | B20: ='Historical Financials'!D11 -> 549.7 | C20: =C8*C19 -> 337.74183 | D20: =D8*D19 -> 388.94011 | E20: =E8*E19 -> 447.89095 | F20: =F8*F19 -> 496.86357
A21: Total Operating Expenses | B21: ='Historical Financials'!D12 -> 4581.3 | C21: =C16+C18+C20 -> 3365.772 | D21: =D16+D18+D20 -> 3960.1174 | E21: =E16+E18+E20 -> 4588.7695 | F21: =F16+F18+F20 -> 5217.0675
A22: Total OpEx % of Revenue | B22: =B21/B8 -> 0.97809518 | C22: =C21/C8 -> 0.578 | D22: =D21/D8 -> 0.56 | E22: =E21/E8 -> 0.543 | F22: =F21/F8 -> 0.525
A23: Operating Income / Loss | B23: ='Historical Financials'!D13 -> -1435.2 | C23: =C13-C21 -> 803.73322 | D23: =D13-D21 -> 1210.7092 | E23: =E13-E21 -> 1713.1484 | F23: =F13-F21 -> 2315.7705
A24: Operating Margin % | B24: =B23/B8 -> -0.30641132 | C24: =C23/C8 -> 0.13802414 | D24: =D23/D8 -> 0.17120633 | E24: =E23/E8 -> 0.20272092 | F24: =F23/F8 -> 0.23303887
A25: Free Cash Flow Margin | B25: =B26/B8 -> 0.23918102 | C25: 0.23 | D25: 0.25 | E25: 0.27 | F25: 0.29
A26: Free Cash Flow | B26: ='Historical Financials'!D16 -> 1120.3 | C26: =C8*C25 -> 1339.3211 | D26: =D8*D25 -> 1767.9096 | E26: =E8*E25 -> 2281.7086 | F26: =F8*F25 -> 2881.8087

Sheet Scenario Analysis
A1: Snowflake FY2027E Scenario Analysis
A2: Figures in $ millions unless otherwise stated
A3: Metric | B3: Downside | C3: Base | D3: Upside
A4: Product Revenue Growth | B4: 0.18 | C4: 0.25 | D4: 0.3
A5: Professional Services Revenue Growth | B5: 0.05 | C5: 0.1 | D5: 0.12
A6: Product Gross Margin | B6: 0.73 | C6: 0.75 | D6: 0.76
A7: Services Gross Margin | B7: -0.1 | C7: -0.1 | D7: -0.05
A8: Sales & Marketing % of Revenue | B8: 0.35 | C8: 0.33 | D8: 0.31
A9: R&D % of Revenue | B9: 0.21 | C9: 0.19 | D9: 0.18
A10: G&A % of Revenue | B10: 0.065 | C10: 0.058 | D10: 0.055
A11: Free Cash Flow Margin | B11: 0.2 | C11: 0.23 | D11: 0.25
A12: Product Revenue | B12: ='Operating Model'!B4*(1+B4) -> 5277.314 | C12: ='Operating Model'!C4*(1+C4) -> 6987.9688 | D12: ='Operating Model'!D4*(1+D4) -> 8866.3347
A13: Professional Services Revenue | B13: ='Operating Model'!B6*(1+'Scenario Analysis'!B5) -> 222.18 | C13: ='Operating Model'!C6*(1+'Scenario Analysis'!C5) -> 256.036 | D13: ='Operating Model'!D6*(1+'Scenario Analysis'!D5) -> 281.5465
A14: Total Revenue | B14: =B12+B13 -> 5499.494 | C14: =C12+C13 -> 7244.0048 | D14: =D12+D13 -> 9147.8812
A15: Product Gross Profit | B15: =B12*B6 -> 3852.4392 | C15: =C12*C6 -> 5240.9766 | D15: =D12*D6 -> 6738.4144
A16: Services Gross Profit | B16: =B13*B7 -> -22.218 | C16: =C13*C7 -> -25.6036 | D16: =D13*D7 -> -14.077325
A17: Total Gross Profit | B17: =B15+B16 -> 3830.2212 | C17: =C15+C16 -> 5215.373 | D17: =D15+D16 -> 6724.3371
A18: Gross Margin % | B18: =B17/B14 -> 0.69646793 | C18: =C17/C14 -> 0.71995714 | D18: =D17/D14 -> 0.73507044
A19: Total Operating Expenses | B19: =B14*(B8+B9+B10) -> 3437.1838 | C19: =C14*(C8+C9+C10) -> 4187.0347 | D19: =D14*(D8+D9+D10) -> 4985.5953
A20: Operating Income | B20: =B17-B19 -> 393.03747 | C20: =C17-C19 -> 1028.3382 | D20: =D17-D19 -> 1738.7418
A21: Operating Margin % | B21: =B20/B14 -> 0.071467933 | C21: =C20/C14 -> 0.14195714 | D21: =D20/D14 -> 0.19007044
A22: Free Cash Flow | B22: =B14*B11 -> 1099.8988 | C22: =C14*C11 -> 1666.1211 | D22: =D14*D11 -> 2286.9703

Sheet KPI Summary
A1: KPI Summary
A2: Figures in $ millions unless otherwise stated
A3: Metric | B3: FY2026A | C3: FY2027E | D3: Change
A4: Product Revenue | B4: ='Operating Model'!B4 -> 4472.3 | C4: ='Operating Model'!C4 -> 5590.375 | D4: =C4/B4-1 -> 0.25
A5: Total Revenue | B5: ='Operating Model'!B8 -> 4683.9 | C5: ='Operating Model'!C8 -> 5823.135 | D5: =C5/B5-1 -> 0.2432236
A6: Gross Profit | B6: ='Operating Model'!B13 -> 3146.1 | C6: ='Operating Model'!C13 -> 4169.5053 | D6: =C6/B6-1 -> 0.3252933
A7: Gross Margin | B7: ='Operating Model'!B14 -> 0.67168385 | C7: ='Operating Model'!C14 -> 0.71602414 | D7: =C7-B7 -> 0.04434029
A8: Operating Income | B8: ='Operating Model'!B23 -> -1435.2 | C8: ='Operating Model'!C23 -> 803.73322 | D8: =C8-B8 -> 2238.9332
A9: Operating Margin | B9: ='Operating Model'!B24 -> -0.30641132 | C9: ='Operating Model'!C24 -> 0.13802414 | D9: =C9-B9 -> 0.44443547
A10: Free Cash Flow | B10: ='Operating Model'!B26 -> 1120.3 | C10: ='Operating Model'!C26 -> 1339.3211 | D10: =C10/B10-1 -> 0.19550214
A11: Free Cash Flow Margin | B11: ='Operating Model'!B25 -> 0.23918102 | C11: ='Operating Model'!C25 -> 0.23 | D11: =C11-B11 -> -0.0091810244
A15: FY2027E Scenario Comparison
A16: Figures in $ millions unless otherwise stated
A17: Metric | B17: Downside | C17: Base | D17: Upside
A18: Total Revenue | B18: ='Scenario Analysis'!B14 -> 5499.494 | C18: ='Scenario Analysis'!C14 -> 7244.0048 | D18: ='Scenario Analysis'!D14 -> 9147.8812
A19: Gross Margin % | B19: ='Scenario Analysis'!B18 -> 0.69646793 | C19: ='Scenario Analysis'!C18 -> 0.71995714 | D19: ='Scenario Analysis'!D18 -> 0.73507044
A20: Operating Income | B20: ='Scenario Analysis'!B20 -> 393.03747 | C20: ='Scenario Analysis'!C20 -> 1028.3382 | D20: ='Scenario Analysis'!D20 -> 1738.7418
A21: Operating Margin % | B21: ='Scenario Analysis'!B21 -> 0.071467933 | C21: ='Scenario Analysis'!C21 -> 0.14195714 | D21: ='Scenario Analysis'!D21 -> 0.19007044
A22: Free Cash Flow | B22: ='Scenario Analysis'!B22 -> 1099.8988 | C22: ='Scenario Analysis'!C22 -> 1666.1211 | D22: ='Scenario Analysis'!D22 -> 2286.9703

Sheet Dashboard
A1: Table 1 — Financial Performance
A2: Figures in $ millions unless otherwise stated
A3: Metric | B3: FY2026A | C3: FY2027E
A4: Product Revenue | B4: ='KPI Summary'!B4 -> 4472.3 | C4: ='KPI Summary'!C4 -> 5590.375
A5: Total Revenue | B5: ='KPI Summary'!B5 -> 4683.9 | C5: ='KPI Summary'!C5 -> 5823.135
A6: Gross Profit | B6: ='KPI Summary'!B6 -> 3146.1 | C6: ='KPI Summary'!C6 -> 4169.5053
A14: Table 2 — Margins
A15: Figures in $ millions unless otherwise stated
A16: Metric | B16: FY2026A | C16: FY2027E
A17: Gross Margin | B17: ='KPI Summary'!B7 -> 0.67168385 | C17: ='KPI Summary'!C7 -> 0.71602414
A18: Operating Margin | B18: ='KPI Summary'!B9 -> -0.30641132 | C18: ='KPI Summary'!C9 -> 0.13802414
A19: Free Cash Flow Margin | B19: ='KPI Summary'!B11 -> 0.23918102 | C19: ='KPI Summary'!C11 -> 0.23
A27: Table 3 — Profitability
A28: Figures in $ millions unless otherwise stated
A29: Metric | B29: FY2026A | C29: FY2027E
A30: Operating Income | B30: ='KPI Summary'!B8 -> -1435.2 | C30: ='KPI Summary'!C8 -> 803.73322
A31: Free Cash Flow | B31: ='KPI Summary'!B10 -> 1120.3 | C31: ='KPI Summary'!C10 -> 1339.3211
A39: Table 4 — Scenario Comparison
A40: Figures in $ millions unless otherwise stated
A41: Metric | B41: Downside | C41: Base | D41: Upside
A42: Total Revenue | B42: ='KPI Summary'!B18 -> 5499.494 | C42: ='KPI Summary'!C18 -> 7244.0048 | D42: ='KPI Summary'!D18 -> 9147.8812
A43: Operating Income | B43: ='KPI Summary'!B20 -> 393.03747 | C43: ='KPI Summary'!C20 -> 1028.3382 | D43: ='KPI Summary'!D20 -> 1738.7418
A44: Free Cash Flow | B44: ='KPI Summary'!B22 -> 1099.8988 | C44: ='KPI Summary'!C22 -> 1666.1211 | D44: ='KPI Summary'!D22 -> 2286.9703

Sheet Power Bi Dashboards1
A1: Table 1: Forecast | B1: Column1 | C1: Column2 | D1: Column3 | E1: Column4 | F1: Column5
A2: Metric | B2: FY2026A | C2: FY2027E | D2: FY2028E | E2: FY2029E | F2: FY2030E
A3: Product Revenue | B3: ='Operating Model'!B4 -> 4472.3 | C3: ='Operating Model'!C4 -> 5590.375 | D3: ='Operating Model'!D4 -> 6820.2575 | E3: ='Operating Model'!E4 -> 8184.309 | F3: ='Operating Model'!F4 -> 9657.4846
A4: Services Revenue | B4: ='Operating Model'!B6 -> 211.6 | C4: ='Operating Model'!C6 -> 232.76 | D4: ='Operating Model'!D6 -> 251.3808 | E4: ='Operating Model'!E6 -> 266.46365 | F4: ='Operating Model'!F6 -> 279.78683
A5: Total Revenue | B5: ='Operating Model'!B8 -> 4683.9 | C5: ='Operating Model'!C8 -> 5823.135 | D5: ='Operating Model'!D8 -> 7071.6383 | E5: ='Operating Model'!E8 -> 8450.7726 | F5: ='Operating Model'!F8 -> 9937.2715
A6: Product Revenue Growth | C6: ='Operating Model'!C5 -> 0.25 | D6: ='Operating Model'!D5 -> 0.22 | E6: ='Operating Model'!E5 -> 0.2 | F6: ='Operating Model'!F5 -> 0.18
A7: Product Gross Profit | B7: ='Operating Model'!B10 -> 3220.1 | C7: ='Operating Model'!C10 -> 4192.7812 | D7: ='Operating Model'!D10 -> 5183.3957 | E7: ='Operating Model'!E10 -> 6301.9179 | F7: ='Operating Model'!F10 -> 7532.838
A8: Product Gross Margin | B8: ='Operating Model'!B9 -> 0.72 | C8: ='Operating Model'!C9 -> 0.75 | D8: ='Operating Model'!D9 -> 0.76 | E8: ='Operating Model'!E9 -> 0.77 | F8: ='Operating Model'!F9 -> 0.78
A9: Operating Income | B9: ='Operating Model'!B23 -> -1435.2 | C9: ='Operating Model'!C23 -> 803.73322 | D9: ='Operating Model'!D23 -> 1210.7092 | E9: ='Operating Model'!E23 -> 1713.1484 | F9: ='Operating Model'!F23 -> 2315.7705
A10: Operating Margin | B10: ='Operating Model'!B24 -> -0.30641132 | C10: ='Operating Model'!C24 -> 0.13802414 | D10: ='Operating Model'!D24 -> 0.17120633 | E10: ='Operating Model'!E24 -> 0.20272092 | F10: ='Operating Model'!F24 -> 0.23303887
A11: Free Cash Flow | B11: ='Operating Model'!B26 -> 1120.3 | C11: ='Operating Model'!C26 -> 1339.3211 | D11: ='Operating Model'!D26 -> 1767.9096 | E11: ='Operating Model'!E26 -> 2281.7086 | F11: ='Operating Model'!F26 -> 2881.8087
A12: FCF Margin | B12: ='Operating Model'!B25 -> 0.23918102 | C12: ='Operating Model'!C25 -> 0.23 | D12: ='Operating Model'!D25 -> 0.25 | E12: ='Operating Model'!E25 -> 0.27 | F12: ='Operating Model'!F25 -> 0.29
A17: SaaS Metrics | B17: Column1 | C17: Column2 | D17: Column3
A18: Metric | B18: FY2024A | C18: FY2025A | D18: FY2026A
A19: Product Revenue | B19: ='Saas Metrics'!B4 -> 2666.8 | C19: ='Saas Metrics'!C4 -> 3462.4 | D19: ='Saas Metrics'!D4 -> 4472.3
A20: Product Growth | C20: ='Saas Metrics'!C5 -> 0.29833508 | D20: ='Saas Metrics'!D5 -> 0.29167629
A21: NRR | B21: ='Saas Metrics'!B6 -> 1.33 | C21: ='Saas Metrics'!C6 -> 1.26 | D21: ='Saas Metrics'!D6 -> 1.25
A22: Customers Over $1M | B22: ='Saas Metrics'!B7 -> 449 | C22: ='Saas Metrics'!C7 -> 576 | D22: ='Saas Metrics'!D7 -> 733
A23: Forbes Global 2000 Customers | B23: ='Saas Metrics'!B9 -> 716 | C23: ='Saas Metrics'!C9 -> 750 | D23: ='Saas Metrics'!D9 -> 790
A24: RPO | B24: ='Saas Metrics'!B10 -> 5174.7 | C24: ='Saas Metrics'!C10 -> 6867.5 | D24: ='Saas Metrics'!D10 -> 9771.5
A25: RPO Growth | C25: ='Saas Metrics'!C11 -> 0.32713008 | D25: ='Saas Metrics'!D11 -> 0.4228613
A26: RPO to Revenue | B26: ='Saas Metrics'!B12 -> 1.8438268 | C26: ='Saas Metrics'!C12 -> 1.8937514 | D26: ='Saas Metrics'!D12 -> 2.0861889
A27: Free Cash Flow | B27: ='Saas Metrics'!B13 -> 778.9 | C27: ='Saas Metrics'!C13 -> 884.1 | D27: ='Saas Metrics'!D13 -> 1120.3
A28: FCF Margin | B28: ='Saas Metrics'!B14 -> 0.2775343 | C28: ='Saas Metrics'!C14 -> 0.2437955 | D28: ='Saas Metrics'!D14 -> 0.23918102
A34: Table 3: Scenario Analysis | B34: Column1 | C34: Column2 | D34: Column3
A35: Metric | B35: Downside | C35: Base | D35: Upside
A36: Product Growth | B36: ='Scenario Analysis'!B4 -> 0.18 | C36: ='Scenario Analysis'!C4 -> 0.25 | D36: ='Scenario Analysis'!D4 -> 0.3
A37: Services Growth | B37: ='Scenario Analysis'!B5 -> 0.05 | C37: ='Scenario Analysis'!C5 -> 0.1 | D37: ='Scenario Analysis'!D5 -> 0.12
A38: Product GM | B38: ='Scenario Analysis'!B6 -> 0.73 | C38: ='Scenario Analysis'!C6 -> 0.75 | D38: ='Scenario Analysis'!D6 -> 0.76
A39: Services GM | B39: ='Scenario Analysis'!B7 -> -0.1 | C39: ='Scenario Analysis'!C7 -> -0.1 | D39: ='Scenario Analysis'!D7 -> -0.05
A40: S&M Percent | B40: ='Scenario Analysis'!B8 -> 0.35 | C40: ='Scenario Analysis'!C8 -> 0.33 | D40: ='Scenario Analysis'!D8 -> 0.31
A41: R&D Percent | B41: ='Scenario Analysis'!B9 -> 0.21 | C41: ='Scenario Analysis'!C9 -> 0.19 | D41: ='Scenario Analysis'!D9 -> 0.18
A42: G&A Percent | B42: ='Scenario Analysis'!B10 -> 0.065 | C42: ='Scenario Analysis'!C10 -> 0.058 | D42: ='Scenario Analysis'!D10 -> 0.055
A43: FCF Margin | B43: ='Scenario Analysis'!B11 -> 0.2 | C43: ='Scenario Analysis'!C11 -> 0.23 | D43: ='Scenario Analysis'!D11 -> 0.25
A44: Total Revenue | B44: ='Scenario Analysis'!B14 -> 5499.494 | C44: ='Scenario Analysis'!C14 -> 7244.0048 | D44: ='Scenario Analysis'!D14 -> 9147.8812
A45: Gross Margin | B45: ='Scenario Analysis'!B18 -> 0.69646793 | C45: ='Scenario Analysis'!C18 -> 0.71995714 | D45: ='Scenario Analysis'!D18 -> 0.73507044
A46: Operating Income | B46: ='Scenario Analysis'!B20 -> 393.03747 | C46: ='Scenario Analysis'!C20 -> 1028.3382 | D46: ='Scenario Analysis'!D20 -> 1738.7418
A47: Operating Margin | B47: ='Scenario Analysis'!B21 -> 0.071467933 | C47: ='Scenario Analysis'!C21 -> 0.14195714 | D47: ='Scenario Analysis'!D21 -> 0.19007044
A48: Free Cash Flow | B48: ='Scenario Analysis'!B22 -> 1099.8988 | C48: ='Scenario Analysis'!C22 -> 1666.1211 | D48: ='Scenario Analysis'!D22 -> 2286.9703

Sheet PowerBi
A1: Metric | B1: FY2024A | C1: FY2025A | D1: FY2026A
A2: Product Revenue | B2: 2666.8 | C2: 3462.4 | D2: 4472.3
A3: Product Growth | C3: 0.298 | D3: 0.292
A4: NRR | B4: 1.33 | C4: 1.26 | D4: 1.25
A5: Customers Over $1M | B5: 449 | C5: 576 | D5: 733
A6: Forbes Global 2000 Customers | B6: 716 | C6: 750 | D6: 790
A7: RPO | B7: 5174.7 | C7: 6867.5 | D7: 9771.5
A8: RPO Growth | C8: 0.327 | D8: 0.423
A9: RPO to Revenue | B9: 1.84 | C9: 1.89 | D9: 2.09
A10: Free Cash Flow | B10: 778.9 | C10: 884.1 | D10: 1120.3
A11: FCF Margin | B11: 0.278 | C11: 0.244 | D11: 0.239
A16: Metric | B16: Downside | C16: Base | D16: Upside
A17: Product Growth | B17: 0.18 | C17: 0.25 | D17: 0.3
A18: Services Growth | B18: 0.05 | C18: 0.1 | D18: 0.12
A19: Product GM | B19: 0.73 | C19: 0.75 | D19: 0.76
A20: Services GM | B20: -0.1 | C20: -0.1 | D20: -0.05
A21: S&M Percent | B21: 0.35 | C21: 0.33 | D21: 0.31
A22: R&D Percent | B22: 0.21 | C22: 0.19 | D22: 0.18
A23: G&A Percent | B23: 0.065 | C23: 0.058 | D23: 0.055
A24: FCF Margin | B24: 0.2 | C24: 0.23 | D24: 0.25
A25: Total Revenue | B25: 5499 | C25: 7244 | D25: 9148
A26: Gross Margin | B26: 0.696 | C26: 0.72 | D26: 0.735
A27: Operating Income | B27: 393 | C27: 1028 | D27: 1739
A28: Operating Margin | B28: 0.071 | C28: 0.142 | D28: 0.19
A29: Free Cash Flow | B29: 1100 | C29: 1666 | D29: 2287
A35: Metric | B35: FY2026A | C35: FY2027E | D35: FY2028E | E35: FY2029E | F35: FY2030E
A36: Product Revenue | B36: 4472.3 | C36: 5590.4 | D36: 6820.3 | E36: 8184.3 | F36: 9657.5
A37: Services Revenue | B37: 211.6 | C37: 232.8 | D37: 251.4 | E37: 266.5 | F37: 279.8
A38: Total Revenue | B38: 4683.9 | C38: 5823.1 | D38: 7071.6 | E38: 8450.8 | F38: 9937.3
A39: Product Revenue Growth | C39: 0.25 | D39: 0.22 | E39: 0.2 | F39: 0.18
A40: Product Gross Profit | B40: 3220.1 | C40: 4192.8 | D40: 5183.4 | E40: 6301.9 | F40: 7532.8
A41: Product Gross Margin | B41: 0.72 | C41: 0.75 | D41: 0.76 | E41: 0.77 | F41: 0.78
A42: Operating Income | B42: -1435.2 | C42: 803.7 | D42: 1210.7 | E42: 1713.1 | F42: 2315.8
A43: Operating Margin | B43: -0.306 | C43: 0.138 | D43: 0.171 | E43: 0.203 | F43: 0.233
A44: Free Cash Flow | B44: 1120.3 | C44: 1339.3 | D44: 1767.9 | E44: 2281.7 | F44: 2881.8
A45: FCF Margin | B45: 0.239 | C45: 0.23 | D45: 0.25 | E45: 0.27 | F45: 0.29
